{
  "project_info": {
    "project_number": "131823254230",
    "project_id": "notes-9e379",
    "storage_bucket": "notes-9e379.appspot.com"
  },
  "client": [
    {
      "client_info": {
        "mobilesdk_app_id": "1:131823254230:android:7c2340975aa7db44702777",
        "android_client_info": {
          "package_name": "com.ronakj.notesapp"
        }
      },
      "oauth_client": [],
      "api_key": [
        {
          "current_key": "AIzaSyAIwKIvSLLKDVHviAfZ8SUbqvj5aoL6r4E"
        }
      ],
      "services": {
        "appinvite_service": {
          "other_platform_oauth_client": []
        }
      }
    }
  ],
  "configuration_version": "1"
}